yaml_io/__init__.py
yaml_io/loader.py
yaml_io-0.1.6.dist-info/licenses/LICENSE.md
yaml_io-0.1.6.dist-info/METADATA
yaml_io-0.1.6.dist-info/WHEEL
yaml_io-0.1.6.dist-info/top_level.txt
yaml_io-0.1.6.dist-info/RECORD
