Metadata-Version: 2.4
Name: yaml-io
Version: 0.1.6
Summary: Import YAML anchors from external files, and export them for re-use in other files
Author: Robbie Mitchell
License: MIT License
Project-URL: Github, https://github.com/superstrong/yaml-io
Project-URL: Issues, https://github.com/superstrong/yaml-io/issues
Classifier: Intended Audience :: Developers
Classifier: Programming Language :: Python :: 3.8
Classifier: Programming Language :: Python :: 3.9
Classifier: Programming Language :: Python :: 3.10
Classifier: Programming Language :: Python :: 3.11
Classifier: Programming Language :: Python :: 3.12
Classifier: Topic :: Software Development :: Libraries :: Python Modules
Requires-Python: >=3.8
License-File: LICENSE.md
Requires-Dist: pyyaml>=5.4
Dynamic: license-file
Dynamic: requires-dist
